{
  "imageId": "KEYPOINTS_TEST",
  "imageWidth": 1536,
  "imageHeight": 3464,
  "pose_keypoints": {
    "CR": {
      "x": 325.3359146118164,
      "y": 652.9692203998566,
      "confidence": 0.999600350856781
    },
    "CL": {
      "x": 1186.880859375,
      "y": 635.115768790245,
      "confidence": 0.9979788661003113
    },
    "IR": {
      "x": 391.3886260986328,
      "y": 2401.9209637641907,
      "confidence": 0.9999650716781616
    },
    "IL": {
      "x": 1133.3184814453125,
      "y": 2395.685761451721,
      "confidence": 0.9998836517333984
    },
    "SR": {
      "x": 665.8096160888672,
      "y": 2495.787197113037,
      "confidence": 0.9997206330299377
    },
    "SL": {
      "x": 857.259521484375,
      "y": 2498.4157729148865,
      "confidence": 0.9995504021644592
    }
  },
  "vertebrae": {
    "C7": {
      "corners": {
        "top_left": {
          "x": 729.8267822265625,
          "y": 502.13665771484375,
          "conf": 0.9997382760047913
        },
        "top_right": {
          "x": 861.72607421875,
          "y": 498.6557312011719,
          "conf": 0.9998646974563599
        },
        "bottom_right": {
          "x": 863.4194946289062,
          "y": 569.0556640625,
          "conf": 0.9998598098754883
        },
        "bottom_left": {
          "x": 731.576171875,
          "y": 572.57177734375,
          "conf": 0.9996887445449829
        },
        "top_mid": {
          "x": 795.7764282226562,
          "y": 500.3961944580078
        },
        "bottom_mid": {
          "x": 797.4978332519531,
          "y": 570.813720703125
        },
        "center": {
          "x": 796.6371307373047,
          "y": 535.6049575805664
        }
      },
      "confidence": 0.8125820755958557,
      "class_id": 0
    },
    "T1": {
      "corners": {
        "top_left": {
          "x": 731.8762817382812,
          "y": 587.074951171875,
          "conf": 0.9998418092727661
        },
        "top_right": {
          "x": 870.80615234375,
          "y": 578.2891845703125,
          "conf": 0.9999018907546997
        },
        "bottom_right": {
          "x": 876.4221801757812,
          "y": 662.2327880859375,
          "conf": 0.9998583793640137
        },
        "bottom_left": {
          "x": 737.49462890625,
          "y": 670.9761962890625,
          "conf": 0.9997578263282776
        },
        "top_mid": {
          "x": 801.3412170410156,
          "y": 582.6820678710938
        },
        "bottom_mid": {
          "x": 806.9584045410156,
          "y": 666.6044921875
        },
        "center": {
          "x": 804.1498107910156,
          "y": 624.6432800292969
        }
      },
      "confidence": 0.8725178241729736,
      "class_id": 1
    },
    "T2": {
      "corners": {
        "top_left": {
          "x": 744.5720825195312,
          "y": 680.70703125,
          "conf": 0.999351441860199
        },
        "top_right": {
          "x": 873.2562255859375,
          "y": 676.04052734375,
          "conf": 0.9994217157363892
        },
        "bottom_right": {
          "x": 876.5103759765625,
          "y": 756.9840087890625,
          "conf": 0.9994699358940125
        },
        "bottom_left": {
          "x": 747.7107543945312,
          "y": 761.6943359375,
          "conf": 0.9994783997535706
        },
        "top_mid": {
          "x": 808.9141540527344,
          "y": 678.373779296875
        },
        "bottom_mid": {
          "x": 812.1105651855469,
          "y": 759.3391723632812
        },
        "center": {
          "x": 810.5123596191406,
          "y": 718.8564758300781
        }
      },
      "confidence": 0.8500520586967468,
      "class_id": 2
    },
    "T3": {
      "corners": {
        "top_left": {
          "x": 753.0614013671875,
          "y": 768.785888671875,
          "conf": 0.9998660087585449
        },
        "top_right": {
          "x": 873.7826538085938,
          "y": 773.0146484375,
          "conf": 0.9999228715896606
        },
        "bottom_right": {
          "x": 870.9059448242188,
          "y": 854.994140625,
          "conf": 0.9998502731323242
        },
        "bottom_left": {
          "x": 749.9019165039062,
          "y": 850.7941284179688,
          "conf": 0.9997292160987854
        },
        "top_mid": {
          "x": 813.4220275878906,
          "y": 770.9002685546875
        },
        "bottom_mid": {
          "x": 810.4039306640625,
          "y": 852.8941345214844
        },
        "center": {
          "x": 811.9129791259766,
          "y": 811.8972015380859
        }
      },
      "confidence": 0.8609728813171387,
      "class_id": 3
    },
    "T4": {
      "corners": {
        "top_left": {
          "x": 749.4886474609375,
          "y": 855.783203125,
          "conf": 0.9997406601905823
        },
        "top_right": {
          "x": 871.8322143554688,
          "y": 867.3265380859375,
          "conf": 0.9998505115509033
        },
        "bottom_right": {
          "x": 864.139892578125,
          "y": 952.88330078125,
          "conf": 0.9998729228973389
        },
        "bottom_left": {
          "x": 741.385986328125,
          "y": 941.2848510742188,
          "conf": 0.9997535347938538
        },
        "top_mid": {
          "x": 810.6604309082031,
          "y": 861.5548706054688
        },
        "bottom_mid": {
          "x": 802.762939453125,
          "y": 947.0840759277344
        },
        "center": {
          "x": 806.7116851806641,
          "y": 904.3194732666016
        }
      },
      "confidence": 0.8972335457801819,
      "class_id": 4
    },
    "T5": {
      "corners": {
        "top_left": {
          "x": 736.91796875,
          "y": 946.7821044921875,
          "conf": 0.99982750415802
        },
        "top_right": {
          "x": 860.8049926757812,
          "y": 960.8737182617188,
          "conf": 0.9998438358306885
        },
        "bottom_right": {
          "x": 852.170654296875,
          "y": 1048.9505615234375,
          "conf": 0.9997321963310242
        },
        "bottom_left": {
          "x": 728.0718383789062,
          "y": 1034.8406982421875,
          "conf": 0.9996709823608398
        },
        "top_mid": {
          "x": 798.8614807128906,
          "y": 953.8279113769531
        },
        "bottom_mid": {
          "x": 790.1212463378906,
          "y": 1041.8956298828125
        },
        "center": {
          "x": 794.4913635253906,
          "y": 997.8617706298828
        }
      },
      "confidence": 0.8959629535675049,
      "class_id": 5
    },
    "T6": {
      "corners": {
        "top_left": {
          "x": 727.1689453125,
          "y": 1043.6658935546875,
          "conf": 0.9998482465744019
        },
        "top_right": {
          "x": 851.3930053710938,
          "y": 1057.9000244140625,
          "conf": 0.9997919201850891
        },
        "bottom_right": {
          "x": 841.6923217773438,
          "y": 1146.5208740234375,
          "conf": 0.9994786381721497
        },
        "bottom_left": {
          "x": 717.2361450195312,
          "y": 1132.3819580078125,
          "conf": 0.9996192455291748
        },
        "top_mid": {
          "x": 789.2809753417969,
          "y": 1050.782958984375
        },
        "bottom_mid": {
          "x": 779.4642333984375,
          "y": 1139.451416015625
        },
        "center": {
          "x": 784.3726043701172,
          "y": 1095.1171875
        }
      },
      "confidence": 0.8881248235702515,
      "class_id": 6
    },
    "T7": {
      "corners": {
        "top_left": {
          "x": 710.7673950195312,
          "y": 1146.8564453125,
          "conf": 0.999011754989624
        },
        "top_right": {
          "x": 848.1455078125,
          "y": 1158.485595703125,
          "conf": 0.9983038902282715
        },
        "bottom_right": {
          "x": 841.968017578125,
          "y": 1247.595947265625,
          "conf": 0.9981268048286438
        },
        "bottom_left": {
          "x": 704.4656982421875,
          "y": 1236.0599365234375,
          "conf": 0.998976469039917
        },
        "top_mid": {
          "x": 779.4564514160156,
          "y": 1152.6710205078125
        },
        "bottom_mid": {
          "x": 773.2168579101562,
          "y": 1241.8279418945312
        },
        "center": {
          "x": 776.3366546630859,
          "y": 1197.2494812011719
        }
      },
      "confidence": 0.8433460593223572,
      "class_id": 7
    },
    "T8": {
      "corners": {
        "top_left": {
          "x": 700.8442993164062,
          "y": 1248.2457275390625,
          "conf": 0.9998065829277039
        },
        "top_right": {
          "x": 841.8818969726562,
          "y": 1259.4945068359375,
          "conf": 0.9997511506080627
        },
        "bottom_right": {
          "x": 835.4578247070312,
          "y": 1352.033935546875,
          "conf": 0.9995866417884827
        },
        "bottom_left": {
          "x": 694.269775390625,
          "y": 1340.9010009765625,
          "conf": 0.9996616840362549
        },
        "top_mid": {
          "x": 771.3630981445312,
          "y": 1253.8701171875
        },
        "bottom_mid": {
          "x": 764.8638000488281,
          "y": 1346.4674682617188
        },
        "center": {
          "x": 768.1134490966797,
          "y": 1300.1687927246094
        }
      },
      "confidence": 0.8726754784584045,
      "class_id": 8
    },
    "T9": {
      "corners": {
        "top_left": {
          "x": 689.9762573242188,
          "y": 1352.08984375,
          "conf": 0.9994522929191589
        },
        "top_right": {
          "x": 838.294677734375,
          "y": 1364.0137939453125,
          "conf": 0.9995130300521851
        },
        "bottom_right": {
          "x": 831.3450927734375,
          "y": 1456.3695068359375,
          "conf": 0.9994025230407715
        },
        "bottom_left": {
          "x": 682.7679443359375,
          "y": 1444.422607421875,
          "conf": 0.9993712306022644
        },
        "top_mid": {
          "x": 764.1354675292969,
          "y": 1358.0518188476562
        },
        "bottom_mid": {
          "x": 757.0565185546875,
          "y": 1450.3960571289062
        },
        "center": {
          "x": 760.5959930419922,
          "y": 1404.2239379882812
        }
      },
      "confidence": 0.8728640079498291,
      "class_id": 9
    },
    "T10": {
      "corners": {
        "top_left": {
          "x": 680.8060913085938,
          "y": 1460.2210693359375,
          "conf": 0.9994946718215942
        },
        "top_right": {
          "x": 834.90673828125,
          "y": 1470.0755615234375,
          "conf": 0.9994989633560181
        },
        "bottom_right": {
          "x": 828.52978515625,
          "y": 1567.21728515625,
          "conf": 0.9994829893112183
        },
        "bottom_left": {
          "x": 674.4243774414062,
          "y": 1557.46142578125,
          "conf": 0.9993904829025269
        },
        "top_mid": {
          "x": 757.8564147949219,
          "y": 1465.1483154296875
        },
        "bottom_mid": {
          "x": 751.4770812988281,
          "y": 1562.33935546875
        },
        "center": {
          "x": 754.666748046875,
          "y": 1513.7438354492188
        }
      },
      "confidence": 0.9064425230026245,
      "class_id": 10
    },
    "T11": {
      "corners": {
        "top_left": {
          "x": 668.1580200195312,
          "y": 1574.0745849609375,
          "conf": 0.9995600581169128
        },
        "top_right": {
          "x": 832.6332397460938,
          "y": 1580.832763671875,
          "conf": 0.9994630217552185
        },
        "bottom_right": {
          "x": 828.7937622070312,
          "y": 1683.8388671875,
          "conf": 0.9992582201957703
        },
        "bottom_left": {
          "x": 664.0691528320312,
          "y": 1677.111572265625,
          "conf": 0.9991750121116638
        },
        "top_mid": {
          "x": 750.3956298828125,
          "y": 1577.4536743164062
        },
        "bottom_mid": {
          "x": 746.4314575195312,
          "y": 1680.4752197265625
        },
        "center": {
          "x": 748.4135437011719,
          "y": 1628.9644470214844
        }
      },
      "confidence": 0.8823439478874207,
      "class_id": 11
    },
    "T12": {
      "corners": {
        "top_left": {
          "x": 655.2264404296875,
          "y": 1694.0396728515625,
          "conf": 0.9994229078292847
        },
        "top_right": {
          "x": 831.601806640625,
          "y": 1696.635986328125,
          "conf": 0.9986990690231323
        },
        "bottom_right": {
          "x": 831.291015625,
          "y": 1804.7611083984375,
          "conf": 0.9953294992446899
        },
        "bottom_left": {
          "x": 654.5867309570312,
          "y": 1801.8297119140625,
          "conf": 0.9983283877372742
        },
        "top_mid": {
          "x": 743.4141235351562,
          "y": 1695.3378295898438
        },
        "bottom_mid": {
          "x": 742.9388732910156,
          "y": 1803.29541015625
        },
        "center": {
          "x": 743.1764984130859,
          "y": 1749.3166198730469
        }
      },
      "confidence": 0.9028244614601135,
      "class_id": 12
    },
    "L1": {
      "corners": {
        "top_left": {
          "x": 656.6224975585938,
          "y": 1833.241943359375,
          "conf": 0.999480664730072
        },
        "top_right": {
          "x": 840.778564453125,
          "y": 1826.2977294921875,
          "conf": 0.9994338154792786
        },
        "bottom_right": {
          "x": 847.3775634765625,
          "y": 1940.52978515625,
          "conf": 0.997490406036377
        },
        "bottom_left": {
          "x": 662.2954711914062,
          "y": 1947.0711669921875,
          "conf": 0.9978779554367065
        },
        "top_mid": {
          "x": 748.7005310058594,
          "y": 1829.7698364257812
        },
        "bottom_mid": {
          "x": 754.8365173339844,
          "y": 1943.8004760742188
        },
        "center": {
          "x": 751.7685241699219,
          "y": 1886.78515625
        }
      },
      "confidence": 0.8428060412406921,
      "class_id": 13
    },
    "L2": {
      "corners": {
        "top_left": {
          "x": 654.961669921875,
          "y": 1968.8004150390625,
          "conf": 0.9996402263641357
        },
        "top_right": {
          "x": 853.2285766601562,
          "y": 1961.8040771484375,
          "conf": 0.9992644190788269
        },
        "bottom_right": {
          "x": 857.9522705078125,
          "y": 2075.787841796875,
          "conf": 0.9991693496704102
        },
        "bottom_left": {
          "x": 659.9080200195312,
          "y": 2083.062255859375,
          "conf": 0.9995763897895813
        },
        "top_mid": {
          "x": 754.0951232910156,
          "y": 1965.30224609375
        },
        "bottom_mid": {
          "x": 758.9301452636719,
          "y": 2079.425048828125
        },
        "center": {
          "x": 756.5126342773438,
          "y": 2022.3636474609375
        }
      },
      "confidence": 0.8361250162124634,
      "class_id": 14
    },
    "L3": {
      "corners": {
        "top_left": {
          "x": 652.0924682617188,
          "y": 2106.32763671875,
          "conf": 0.9997654557228088
        },
        "top_right": {
          "x": 866.9141845703125,
          "y": 2103.08984375,
          "conf": 0.9996637105941772
        },
        "bottom_right": {
          "x": 869.6316528320312,
          "y": 2227.850341796875,
          "conf": 0.999478280544281
        },
        "bottom_left": {
          "x": 654.9197998046875,
          "y": 2231.34423828125,
          "conf": 0.9993896484375
        },
        "top_mid": {
          "x": 759.5033264160156,
          "y": 2104.708740234375
        },
        "bottom_mid": {
          "x": 762.2757263183594,
          "y": 2229.5972900390625
        },
        "center": {
          "x": 760.8895263671875,
          "y": 2167.1530151367188
        }
      },
      "confidence": 0.9473122358322144,
      "class_id": 15
    },
    "L4": {
      "corners": {
        "top_left": {
          "x": 650.289794921875,
          "y": 2256.7392578125,
          "conf": 0.9999434947967529
        },
        "top_right": {
          "x": 871.627685546875,
          "y": 2258.23095703125,
          "conf": 0.9999240636825562
        },
        "bottom_right": {
          "x": 871.212646484375,
          "y": 2384.353759765625,
          "conf": 0.9998853206634521
        },
        "bottom_left": {
          "x": 650.1561279296875,
          "y": 2383.398681640625,
          "conf": 0.9999101161956787
        },
        "top_mid": {
          "x": 760.958740234375,
          "y": 2257.485107421875
        },
        "bottom_mid": {
          "x": 760.6843872070312,
          "y": 2383.876220703125
        },
        "center": {
          "x": 760.8215637207031,
          "y": 2320.6806640625
        }
      },
      "confidence": 0.8709068894386292,
      "class_id": 16
    },
    "L5": {
      "corners": {
        "top_left": {
          "x": 647.5858764648438,
          "y": 2408.602783203125,
          "conf": 0.999085545539856
        },
        "top_right": {
          "x": 875.7246704101562,
          "y": 2412.131103515625,
          "conf": 0.9992623925209045
        },
        "bottom_right": {
          "x": 871.2986450195312,
          "y": 2522.907958984375,
          "conf": 0.9978954792022705
        },
        "bottom_left": {
          "x": 643.3544921875,
          "y": 2519.044189453125,
          "conf": 0.9984112977981567
        },
        "top_mid": {
          "x": 761.6552734375,
          "y": 2410.366943359375
        },
        "bottom_mid": {
          "x": 757.3265686035156,
          "y": 2520.97607421875
        },
        "center": {
          "x": 759.4909210205078,
          "y": 2465.6715087890625
        }
      },
      "confidence": 0.7817521095275879,
      "class_id": 17
    }
  }
}